Metadata-Version: 2.1
Name: sam-29082022-distributions
Version: 0.1
Summary: Gaussian, Binomial distributions
